{"inkVersion":21,"root":[["#","^speaker:Bob ","/#","#","^portrait:Strict","/#","^Morning Matt - He glances at your appearance -","\n","^Good to see you're actually taking your presentation at this company seriously for once...","\n","ev","str","^Thanks..?","/str","/ev",{"*":"0.c-0","flg":20},"ev","str","^Yeah I guess...","/str","/ev",{"*":"0.c-1","flg":20},{"c-0":["^ ",{"->":"StillDoesntExcuseMoping"},"\n",{"->":"0.g-0"},{"#f":5}],"c-1":["^ ",{"->":"YouGuess"},"\n",{"->":"0.g-0"},{"#f":5}],"g-0":["done",{"#f":5}]}],"done",{"YouGuess":[["^The same can't be said for all that moping you're doing, you're still stuck on what happened aren't you?","\n","ev","str","^No...","/str","/ev",{"*":".^.c-0","flg":20},"ev","str","^I'm still working through things...","/str","/ev",{"*":".^.c-1","flg":20},"ev","str","^Why do you even care?","/str","/ev",{"*":".^.c-2","flg":20},{"c-0":["^ ",{"->":"DoesntLookLikeIt"},"\n",{"#f":5}],"c-1":["^ ",{"->":"Typical"},"\n",{"#f":5}],"c-2":["^ ",{"->":"Pathetic"},"\n",{"#f":5}]}],{"#f":1}],"StillDoesntExcuseMoping":[["^Though it doesn't excuse all that moping you're doing...","\n","^You still haven't gotten over what happened yet have you?","\n","ev","str","^Not really...","/str","/ev",{"*":".^.c-0","flg":20},"ev","str","^Yes I have actually","/str","/ev",{"*":".^.c-1","flg":20},"ev","str","^Why do you even care?","/str","/ev",{"*":".^.c-2","flg":20},{"c-0":["^ ",{"->":"ItsBeenAges"},"\n",{"#f":5}],"c-1":["^ ",{"->":"DoesntLookLikeIt"},"\n",{"#f":5}],"c-2":["^ ",{"->":"Pathetic"},"\n",{"#f":5}]}],{"#f":1}],"ItsBeenAges":[["^Mathew it's been how long now? The way you betrayed Cyrus's little girl was cowardly and pathetic but even she was able to move on from what happened.","\n","^You need to get your act together and actually TRY to move forward.","\n","ev","str","^I know. I'm trying...","/str","/ev",{"*":".^.c-0","flg":20},"ev","str","^*Look away*","/str","/ev",{"*":".^.c-1","flg":20},{"c-0":["^ ",{"->":"TryHarder"},"\n",{"#f":5}],"c-1":["^ ",{"->":"DoItForYourself"},"\n",{"#f":5}]}],{"#f":1}],"DoItForYourself":[["^Do it for yourself if not for her.","\n","^I'll be seeing you Matt.","\n","ev","str","^*Nod head*","/str","/ev",{"*":".^.c-0","flg":20},"ev","str","^See you...","/str","/ev",{"*":".^.c-1","flg":20},{"c-0":["^ ","done","\n",{"#f":5}],"c-1":["^ ","done","\n",{"#f":5}]}],{"#f":1}],"TryHarder":[["^From the looks of things, you need to try harder. You can start by making sure you get your work done and avoid slacking off. - He gestures to Dillon -","\n","^I'll be seeing you Matt","\n","ev","str","^See you...","/str","/ev",{"*":".^.c-0","flg":20},"ev","str","^*Say nothing*","/str","/ev",{"*":".^.c-1","flg":20},{"c-0":["^ ","done","\n",{"#f":5}],"c-1":["^ ","done","\n",{"#f":5}]}],{"#f":1}],"DoesntLookLikeIt":[["^Mhm sure...","\n","^Look it's obvious you're not over it, you can't deny that. What I don't understand is why you're still acting like she'll come back to you after what you did?","\n","ev","str","^I...don't know...","/str","/ev",{"*":".^.c-0","flg":20},"ev","str","^*Look away*","/str","/ev",{"*":".^.c-1","flg":20},{"c-0":["^ ",{"->":"DontKnow"},"\n",{"#f":5}],"c-1":["^ ",{"->":"DontKnow"},"\n",{"#f":5}]}],{"#f":1}],"DontKnow":[["^You're a grown man Matt, people can only be so patient with immature behaviour.","\n","^I suggest you start acting your age for once and get your life together, you can start by getting your work done instead of getting lost in the clouds.","\n","^I'll be going now","\n","ev","str","^Bye...","/str","/ev",{"*":".^.c-0","flg":20},"ev","str","^*Say nothing*","/str","/ev",{"*":".^.c-1","flg":20},"ev","str","^Whatever asshole","/str","/ev",{"*":".^.c-2","flg":20},{"c-0":["^ ","done","\n",{"#f":5}],"c-1":["^ ","done","\n",{"#f":5}],"c-2":["^ ",{"->":"Backchat"},"\n",{"#f":5}]}],{"#f":1}],"Backchat":[["^You may be dressed well but your attitude needs some work.","\n","^Cursing won't make it any better Matt, I'll see to it that the boss has a word with you.","\n","ev","str","^*Say nothing*","/str","/ev",{"*":".^.c-0","flg":20},"ev","str","^*Take a swing at Bob*","/str","/ev",{"*":".^.c-1","flg":20},{"c-0":["^ ","done","\n",{"#f":5}],"c-1":["^ ",{"->":"AngryBob"},"\n",{"#f":5}]}],{"#f":1}],"AngryBob":[[["^!?","\n","^MATHEW I WILL SEE TO IT YOU ARE FIRED IMMEDIATELY!","\n","ev","str","^*Roll eyes*","/str","/ev",{"*":".^.c-0","flg":20},"ev","str","^Do it!","/str","/ev",{"*":".^.c-1","flg":20},{"c-0":["^ ","done","\n",{"#f":5}],"c-1":["^ ","done","\n",{"#f":5}],"#f":5,"#n":"g-0"}],null],{"#f":1}],"Typical":[["^Typical of you isn't it Mathew? Still \"working through things\"? How long did you expect she was going to wait for you? Years? Decades? The world doesn't revolve around you you know?","\n","^The sooner you realise that, the better off you'll be.","\n","ev","str","^I know","/str","/ev",{"*":".^.c-0","flg":20},"ev","str","^I understand","/str","/ev",{"*":".^.c-1","flg":20},"ev","str","^It's none of your business asshole!","/str","/ev",{"*":".^.c-2","flg":20},{"c-0":["^ ",{"->":"ActLikeIt"},"\n",{"#f":5}],"c-1":["^ ",{"->":"ActLikeIt"},"\n",{"#f":5}],"c-2":["^ ",{"->":"AgressiveBob"},"\n",{"#f":5}]}],{"#f":1}],"AgressiveBob":[["^HOW ABOUT YOU WATCH YOUR TONE WHEN SPEAKING TO A SENIOR COLLEGUE!?","\n","ev","str","^How about \"No\"?","/str","/ev",{"*":".^.c-0","flg":20},"ev","str","^*Punch Bob*","/str","/ev",{"*":".^.c-1","flg":20},"ev","str","^*Appologise*","/str","/ev",{"*":".^.c-2","flg":20},{"c-0":["^ ",{"->":"AngryBob"},"\n",{"#f":5}],"c-1":["^ ",{"->":"AngryBob"},"\n",{"#f":5}],"c-2":["^ ",{"->":"AnnoyedBob"},"\n",{"#f":5}]}],{"#f":1}],"AnnoyedBob":[["^You need to learn some respect Mathew, don't ever speak to me like that again.","\n","^The boss will be having a word with you later today to discuss your behaviour, I suggest you get your act together before then.","\n","ev","str","^*Say nothing*","/str","/ev",{"*":".^.c-0","flg":20},"ev","str","^Whatever","/str","/ev",{"*":".^.c-1","flg":20},{"c-0":["^ ","done","\n",{"#f":5}],"c-1":["^ ","done","\n",{"#f":5}]}],{"#f":1}],"ActLikeIt":[["^Good, then act like it.","\n","^Goodbye Matt.","\n","ev","str","^Bye...","/str","/ev",{"*":".^.c-0","flg":20},"ev","str","^Whatever asshole","/str","/ev",{"*":".^.c-1","flg":20},{"c-0":["^ ","done","\n",{"#f":5}],"c-1":["^ ",{"->":"Backchat"},"\n",{"#f":5}]}],{"#f":1}],"Pathetic":[["^Because it's pathetic seeing you drag yourself around like a toddler having a tantrum. You don't get to be the one who recieves sympathy for acting like a coward, Cyrus's daughter deserved better and you know it.","\n","ev","str","^I know...","/str","/ev",{"*":".^.c-0","flg":20},"ev","str","^*Glare*","/str","/ev",{"*":".^.c-1","flg":20},"ev","str","^It's none of your business, fuck off!","/str","/ev",{"*":".^.c-2","flg":20},{"c-0":["^ ",{"->":"StartGettingLifeTogether"},"\n",{"#f":5}],"c-1":["^ ",{"->":"Glare"},"\n",{"#f":5}],"c-2":["^ ",{"->":"Backchat"},"\n",{"#f":5}]}],{"#f":1}],"Glare":[["^Glaring at me won't make a difference Matt.","\n","ev","str","^...","/str","/ev",{"*":".^.c-0","flg":20},{"c-0":["^ ",{"->":"StartGettingLifeTogether"},"\n",{"#f":5}]}],{"#f":1}],"StartGettingLifeTogether":[["^You need to get your life together and stop living in the past, maybe you'll finally learn to act your age and we won't have to have this discussion in the future.","\n","^I'll be seeing you Matt, don't slack off, the boss won't take kindly to it if he catches you again.","\n","ev","str","^*Nod head*","/str","/ev",{"*":".^.c-0","flg":20},"ev","str","^See you...","/str","/ev",{"*":".^.c-1","flg":20},"ev","str","^Get off my damn case already","/str","/ev",{"*":".^.c-2","flg":20},{"c-0":["^ ","done","\n",{"#f":5}],"c-1":["^ ","done","\n",{"#f":5}],"c-2":["^ ",{"->":"Backchat"},"\n",{"#f":5}]}],{"#f":1}],"#f":1}],"listDefs":{}}