{"inkVersion":21,"root":[["#","^speaker:Angy Man ","/#","#","^portrait:Barret","/#","^The fuck are you looking at?!","\n","ev","str","^Nothing, sorry. Just passing through.","/str","/ev",{"*":"0.c-0","flg":20},"ev","str","^Are you alright?","/str","/ev",{"*":"0.c-1","flg":20},"ev","str","^ Obviously you, asshole.","/str","/ev",{"*":"0.c-2","flg":20},{"c-0":["^ ",{"->":"endConvo"},"\n",{"->":"0.g-0"},{"#f":5}],"c-1":["^ ",{"->":"IDontNeedYourPity"},"\n",{"->":"0.g-0"},{"#f":5}],"c-2":["^ ",{"->":"Fight"},"\n",{"->":"0.g-0"},{"#f":5}],"g-0":["done",{"#f":5}]}],"done",{"IDontNeedYourPity":[["^What do you think? Get out of here.","\n","ev","str","^Did you...want to talk about it?","/str","/ev",{"*":".^.c-0","flg":20},"ev","str","^I'll leave you to it","/str","/ev",{"*":".^.c-1","flg":20},{"c-0":["^ ",{"->":"what"},"\n",{"#f":5}],"c-1":["^ ",{"->":"endConvo"},"\n",{"#f":5}]}],{"#f":1}],"what":[[["^Scoffs - Talk about it? What are you, my therapist? What's in it for you?","\n","ev","str","^Nothing, sorry, I just thought I'd ask.","/str","/ev",{"*":".^.c-0","flg":20},"ev","str","^I dunno. Boredom","/str","/ev",{"*":".^.c-1","flg":20},"ev","str","^Nothing, just thought it would be nice.","/str","/ev",{"*":".^.c-2","flg":20},"ev","str","^Sorry, it's none of my business, I'll let you be.","/str","/ev",{"*":".^.c-3","flg":20},{"c-0":["^ ",{"->":"NoOffence"},"\n",{"#f":5}],"c-1":["^ ",{"->":"Boredom"},"\n",{"#f":5}],"c-2":["^ ",{"->":"ImNiceGuy"},"\n",{"#f":5}],"c-3":["^ ",{"->":"PolitelyEndConvo"},"\n",{"#f":5}],"#f":5,"#n":"g-0"}],null],{"#f":1}],"PolitelyEndConvo":["^Whatever.","\n","done",{"#f":1}],"NoOffence":[["^Heh...yeah no offence but it's a little weird to just spill my guts out to some stranger.","\n","^Sticking your nose in someone else's business instead of just minding your own...","\n","ev","str","^Sorry I didn't mean to pry.","/str","/ev",{"*":".^.c-0","flg":20},"ev","str","^Yeah sorry, I just thought I should check.","/str","/ev",{"*":".^.c-1","flg":20},{"c-0":["^ ",{"->":"why"},"\n",{"#f":5}],"c-1":["^ ",{"->":"ImNiceGuy"},"\n",{"#f":5}]}],{"#f":1}],"Boredom":[["^You think this is some kind of entertainment?","\n","^I could fuck you up you know?","\n","ev","str","^I'm sure you could","/str","/ev",{"*":".^.c-0","flg":20},"ev","str","^Nah.","/str","/ev",{"*":".^.c-1","flg":20},{"c-0":["^ ",{"->":"why"},"\n",{"#f":5}],"c-1":["\n","^The fuck you mean 'nah'? You don't think I could?! ",{"->":"Fight"},"\n",{"#f":5}]}],{"#f":1}],"ImNiceGuy":[["^...","\n","^You really would come up to some random guy like me just to be nice?","\n","^Heh you must be all kinds of crazy, man.","\n",["^Laughs to himself -","\n","^Damn, I haven't laughed like this in a long time...you got a name? Let me buy you a drink.","\n","ev","str","^ Thanks, it's Matt ","/str","/ev",{"*":".^.c-0","flg":20},"ev","str","^ It's Matt. I appreciate the offer but I'll be alright, I'm glad I could help out though, take care. ","/str","/ev",{"*":".^.c-1","flg":20},{"c-0":["^ ",{"->":"HeBuyDrinkForU"},"\n",{"#f":5}],"c-1":["^ ",{"->":"LeaveAngryBar"},"\n",{"#f":5}],"#f":5,"#n":"g-0"}],null],{"#f":1}],"HeBuyDrinkForU":["^Good to meet ya Matt, I'm Angry Bar Dude.","\n","done",{"#f":1}],"LeaveAngryBar":["^No worries Matt, have a good one.","\n","done",{"#f":1}],"why":[["^Then why are you still in here?","\n","ev","str","^Because I want to help, it couldn't hurt to at least let me try right?","/str","/ev",{"*":".^.c-0","flg":20},"ev","str","^I actually dont know","/str","/ev",{"*":".^.c-1","flg":20},{"c-0":["^ ",{"->":"ImNiceGuy"},"\n",{"#f":5}],"c-1":["^ ","\n","^Then scram. I don't want you buzzing about in my ear. ","done","\n",{"#f":5}]}],{"#f":1}],"Fight":[["^You looking for a fucking fight punk!?","\n","ev","str","^Sorry, nevermind.","/str","/ev",{"*":".^.c-0","flg":20},"ev","str","^I don't know, are you!? - Throw a punch -","/str","/ev",{"*":".^.c-1","flg":20},{"c-0":["^ ",{"->":"endConvo"},"\n",{"#f":5}],"c-1":["^ ",{"->":"buhBye"},"\n",{"#f":5}]}],{"#f":1}],"buhBye":[[["^Laughs-","\n","^Big mistake buddy.","\n",["^punch -","\n","done",{"#f":5,"#n":"g-1"}],{"#f":5,"#n":"g-0"}],null],{"#f":1}],"endConvo":["^Hmph.","\n","^Thats what I fucking thought. Beat it.","\n","done",{"#f":1}],"#f":1}],"listDefs":{}}